{
  "main": {
    "id": "75ac74ed0d3bf42f",
    "type": "split",
    "children": [
      {
        "id": "cb575b96a0dd2d19",
        "type": "tabs",
        "children": [
          {
            "id": "6d8cb050d728dd71",
            "type": "leaf",
            "state": {
              "type": "markdown",
              "state": {
                "file": "00 - Dashboard.md",
                "mode": "preview",
                "source": true
              },
              "icon": "lucide-file",
              "title": "00 - Dashboard"
            }
          }
        ]
      }
    ],
    "direction": "vertical"
  },
  "left": {
    "id": "fbe796549d86d044",
    "type": "split",
    "children": [
      {
        "id": "032d60176aee102d",
        "type": "tabs",
        "children": [
          {
            "id": "d20335535a2fc31e",
            "type": "leaf",
            "state": {
              "type": "file-explorer",
              "state": {
                "sortOrder": "alphabetical",
                "autoReveal": false
              },
              "icon": "lucide-folder-closed",
              "title": "Files"
            }
          },
          {
            "id": "2e0ba0a1e3db21cb",
            "type": "leaf",
            "state": {
              "type": "search",
              "state": {
                "query": "",
                "matchingCase": false,
                "explainSearch": false,
                "collapseAll": false,
                "extraContext": false,
                "sortOrder": "alphabetical"
              },
              "icon": "lucide-search",
              "title": "Search"
            }
          },
          {
            "id": "4e6c3b99facc1d22",
            "type": "leaf",
            "state": {
              "type": "bookmarks",
              "state": {},
              "icon": "lucide-bookmark",
              "title": "Bookmarks"
            }
          }
        ]
      }
    ],
    "direction": "horizontal",
    "width": 300
  },
  "right": {
    "id": "afa3eba4ac3ab4a8",
    "type": "split",
    "children": [
      {
        "id": "7c1aca7001479d7c",
        "type": "tabs",
        "children": [
          {
            "id": "fac1a910ef2d4cd4",
            "type": "leaf",
            "state": {
              "type": "backlink",
              "state": {
                "file": "00 - Dashboard.md",
                "collapseAll": false,
                "extraContext": false,
                "sortOrder": "alphabetical",
                "showSearch": false,
                "searchQuery": "",
                "backlinkCollapsed": false,
                "unlinkedCollapsed": true
              },
              "icon": "links-coming-in",
              "title": "Backlinks for 00 - Dashboard"
            }
          },
          {
            "id": "f655eb840bb31a52",
            "type": "leaf",
            "state": {
              "type": "outgoing-link",
              "state": {
                "file": "00 - Dashboard.md",
                "linksCollapsed": false,
                "unlinkedCollapsed": true
              },
              "icon": "links-going-out",
              "title": "Outgoing links from 00 - Dashboard"
            }
          },
          {
            "id": "fd6c4ff491fa7848",
            "type": "leaf",
            "state": {
              "type": "tag",
              "state": {
                "sortOrder": "frequency",
                "useHierarchy": true,
                "showSearch": false,
                "searchQuery": ""
              },
              "icon": "lucide-tags",
              "title": "Tags"
            }
          },
          {
            "id": "821e185dd5f28784",
            "type": "leaf",
            "state": {
              "type": "outline",
              "state": {
                "file": "00 - Dashboard.md",
                "followCursor": false,
                "showSearch": false,
                "searchQuery": ""
              },
              "icon": "lucide-list",
              "title": "Outline of 00 - Dashboard"
            }
          },
          {
            "id": "3b07696d313576e3",
            "type": "leaf",
            "state": {
              "type": "calendar",
              "state": {},
              "icon": "calendar-with-checkmark",
              "title": "Calendar"
            }
          }
        ]
      }
    ],
    "direction": "horizontal",
    "width": 300,
    "collapsed": true
  },
  "left-ribbon": {
    "hiddenItems": {
      "switcher:Open quick switcher": false,
      "graph:Open graph view": false,
      "canvas:Create new canvas": false,
      "daily-notes:Open today's daily note": false,
      "templates:Insert template": false,
      "command-palette:Open command palette": false,
      "bases:Create new base": false,
      "templater-obsidian:Templater": false,
      "quickadd:QuickAdd": false
    }
  },
  "active": "6d8cb050d728dd71",
  "lastOpenFiles": [
    "README.md",
    "AGENTS.md",
    "00 - Dashboard.md"
  ]
}